cpca/__init__.py
cpca/drawer.py
cpca/exceptions.py
cpca/matcher.py
cpca/structures.py
cpca/resources/56_nations.csv
cpca/resources/__init__.py
cpca/resources/adcodes.csv
cpca-0.5.5.dist-info/LICENSE
cpca-0.5.5.dist-info/METADATA
cpca-0.5.5.dist-info/WHEEL
cpca-0.5.5.dist-info/top_level.txt
cpca-0.5.5.dist-info/RECORD
