Metadata-Version: 1.1
Name: cpca
Version: 0.5.5
Summary: Chinese Province, City and Area Recognition Utilities
Home-page: https://github.com/DQinYuan/chinese_province_city_area_mapper
Author: DQinYuan
Author-email: sa517067@mail.ustc.edu.cn
License: MIT
Keywords: Simplified Chinese,Chinese geographic information,Chinese province city and area recognition and map
Platform: UNKNOWN
Classifier: Intended Audience :: Developers
Classifier: License :: OSI Approved :: MIT License
Classifier: Operating System :: OS Independent
Classifier: Natural Language :: Chinese (Simplified)
Classifier: Programming Language :: Python :: 3.6
Classifier: Topic :: Text Processing
Classifier: Topic :: Text Processing :: Indexing
